pyfemtet/__init__.py
pyfemtet/_i18n/1. make_pot_and_update_po.bat
pyfemtet/_i18n/2. build_mo.bat
pyfemtet/_i18n/__init__.py
pyfemtet/_i18n/babel.cfg
pyfemtet/_i18n/i18n.py
pyfemtet/_i18n/locales/ja/LC_MESSAGES/messages.mo
pyfemtet/_i18n/locales/ja/LC_MESSAGES/messages.po
pyfemtet/_i18n/locales/messages.pot
pyfemtet/_i18n/messages.py
pyfemtet/_util/__init__.py
pyfemtet/_util/closing.py
pyfemtet/_util/dask_util.py
pyfemtet/_util/df_util.py
pyfemtet/_util/excel_macro_util.py
pyfemtet/_util/excel_parse_util.py
pyfemtet/_util/femtet_access_inspection.py
pyfemtet/_util/femtet_autosave.py
pyfemtet/_util/femtet_exit.py
pyfemtet/_util/femtet_version.py
pyfemtet/_util/helper.py
pyfemtet/_util/process_util.py
pyfemtet/_util/sample.xlsx
pyfemtet/_util/solidworks_variable.py
pyfemtet/_util/str_enum.py
pyfemtet/_util/symbol_support_for_param_name.py
pyfemtet/core.py
pyfemtet/dispatch_extensions/__init__.py
pyfemtet/dispatch_extensions/_impl.py
pyfemtet/logger/__init__.py
pyfemtet/logger/_impl.py
pyfemtet/opt/__init__.py
pyfemtet/opt/exceptions.py
pyfemtet/opt/femopt.py
pyfemtet/opt/history/__init__.py
pyfemtet/opt/history/_history.py
pyfemtet/opt/history/_hypervolume.py
pyfemtet/opt/history/_optimality.py
pyfemtet/opt/interface/__init__.py
pyfemtet/opt/interface/_base_interface.py
pyfemtet/opt/interface/_dummy_classes.py
pyfemtet/opt/interface/_excel_interface/__init__.py
pyfemtet/opt/interface/_excel_interface/debug-excel-interface.xlsm
pyfemtet/opt/interface/_excel_interface/excel_interface.py
pyfemtet/opt/interface/_femtet_interface/__init__.py
pyfemtet/opt/interface/_femtet_interface/_femtet_parametric.py
pyfemtet/opt/interface/_femtet_interface/femtet_interface.py
pyfemtet/opt/interface/_femtet_with_nx_interface/__init__.py
pyfemtet/opt/interface/_femtet_with_nx_interface/femtet_with_nx_interface.py
pyfemtet/opt/interface/_femtet_with_nx_interface/model1.prt
pyfemtet/opt/interface/_femtet_with_nx_interface/model1.x_t
pyfemtet-1.7.2.dist-info/METADATA
pyfemtet-1.7.2.dist-info/WHEEL
pyfemtet-1.7.2.dist-info/entry_points.txt
pyfemtet-1.7.2.dist-info/licenses/LICENSE
pyfemtet-1.7.2.dist-info/licenses/LICENSE_THIRD_PARTY.txt
pyfemtet-1.7.2.dist-info/RECORD
