Metadata-Version: 2.4
Name: pyfemtet
Version: 1.7.2
Summary: Design parameter optimization using Femtet.
License-Expression: MIT
License-File: LICENSE
License-File: LICENSE_THIRD_PARTY.txt
Author: pyfemtet
Author-email: 148934231+pyfemtet@users.noreply.github.com
Requires-Python: >= 3.10, < 3.15
Classifier: Programming Language :: Python :: 3
Classifier: Programming Language :: Python :: 3.10
Classifier: Programming Language :: Python :: 3.11
Classifier: Programming Language :: Python :: 3.12
Classifier: Programming Language :: Python :: 3.13
Classifier: Programming Language :: Python :: 3.14
Requires-Dist: babel (>=2.15.0,<3)
Requires-Dist: botorch (>=0.12.0,<0.15.0)
Requires-Dist: colorlog (>=6.8.0,<7)
Requires-Dist: dash (>=2.17.0,<3)
Requires-Dist: dash-bootstrap-components (>=1.5.0,<2)
Requires-Dist: dask (>=2024.12.1,<2024.13.0)
Requires-Dist: distributed (>=2024.12.1,<2024.13.0)
Requires-Dist: femtetutils (>=1.0.0,<2) ; sys_platform == "win32"
Requires-Dist: fire (>=0.7)
Requires-Dist: frozendict (>=2.4.6)
Requires-Dist: numpy (>=2.0.0,<3)
Requires-Dist: openpyxl (>=3.1.2,<4)
Requires-Dist: optuna (>=4.5.0,<4.6.0)
Requires-Dist: optuna-integration (>=3.6.0,<5.0.0)
Requires-Dist: packaging (>=25.0)
Requires-Dist: pandas (>=2.2.3,<3)
Requires-Dist: plotly (>=5.22.0,<6)
Requires-Dist: psutil (>=5.9.6,<6)
Requires-Dist: pywin32 (>=310) ; sys_platform == "win32"
Requires-Dist: pyyaml (>=6.0.2,<7)
Requires-Dist: scipy (>=1.11.4,<2)
Requires-Dist: torch
Requires-Dist: tqdm (>=4.66.1,<5)
Project-URL: Repository, https://github.com/pyfemtet/pyfemtet
